processing/__init__.py
processing/gui/procedure_config_view.py
processing/gui/toml_editor.py
processing/main.py
processing/module.py
processing/modules/__init__.py
processing/modules/air_pressure_correction.py
processing/modules/available_modules.py
processing/modules/create_bottlefile.py
processing/modules/create_mbf.py
processing/modules/external_functions.py
processing/modules/geomar_wildedit.py
processing/modules/join_btl.py
processing/modules/seabird_functions.py
processing/procedure.py
processing/seabird/__init__.py
processing/seabird/module.py
processing/seabird/routine.py
processing/seabird/step.py
processing/settings.py
processing/utils.py
processing/vis_config.toml
processing/visualize.py
ctd_processing-1.11.7.dist-info/METADATA
ctd_processing-1.11.7.dist-info/WHEEL
ctd_processing-1.11.7.dist-info/entry_points.txt
ctd_processing-1.11.7.dist-info/licenses/LICENSE
ctd_processing-1.11.7.dist-info/RECORD
